hamkit/itu/__about__.py
hamkit/itu/__init__.py
hamkit/itu/_itu.py
hamkit_itu-0.0.1a1.dist-info/METADATA
hamkit_itu-0.0.1a1.dist-info/WHEEL
hamkit_itu-0.0.1a1.dist-info/licenses/LICENSE
hamkit_itu-0.0.1a1.dist-info/RECORD
